{
  "tracks": [
    {"url": "/assets/1.mp4", "duration": 5.005000 },
    {"url": "/assets/2.mp4", "duration": 8.409000 },
    {"url": "/assets/3.mp4", "duration": 5.206000 },
    {"url": "/assets/4.mp4", "duration": 34.702000 },
    {"url": "/assets/5.mp4", "duration": 36.504000 },
    {"url": "/assets/6.mp4", "duration": 37.371000 },
    {"url": "/assets/7.mp4", "duration": 6.807000 },
    {"url": "/assets/8.mp4", "duration": 3.070000 },
    {"url": "/assets/9.mp4", "duration": 3.404000 },
    {"url": "/assets/10.mp4", "duration": 17.151000 },
    {"url": "/assets/11.mp4", "duration": 48.082000 },
    {"url": "/assets/12.mp4", "duration": 26.327000 },
    {"url": "/assets/13.mp4", "duration": 29.363000 },
    {"url": "/assets/14.mp4", "duration": 16.217000 },
    {"url": "/assets/15.mp4", "duration": 8.142000 },
    {"url": "/assets/16.mp4", "duration": 7.108000 },
    {"url": "/assets/17.mp4", "duration": 17.151000 },
    {"url": "/assets/18.mp4", "duration": 10.378000 },
    {"url": "/assets/19.mp4", "duration": 6.974000 },
    {"url": "/assets/20.mp4", "duration": 9.009000 }
  ]
}
